LICENSE
MANIFEST.in
README.rst
setup.py
pygster_parsers/KV.py
pygster_parsers/OBNginxLatency.py
pygster_parsers/__init__.py
pygster_parsers.egg-info/PKG-INFO
pygster_parsers.egg-info/SOURCES.txt
pygster_parsers.egg-info/dependency_links.txt
pygster_parsers.egg-info/not-zip-safe
pygster_parsers.egg-info/requires.txt
pygster_parsers.egg-info/top_level.txt