Metadata-Version: 1.0
Name: pygster-parsers
Version: 2.0.0
Summary: Pygster Parsers
Home-page: https://github.com/OnBeep/pygster_parsers
Author: Greg Albrecht
Author-email: gba@onbeep.com
License: Copyright 2014 OnBeep, Inc.
